gavanon/__init__.py
gavanon/_element.py
gavanon/process.py
gavanon/py.typed
gavanon/skill.py
gavanon/sources.py
gavanon/transistor.py
gavanon-0.0.dist-info/LICENSE
gavanon-0.0.dist-info/METADATA
gavanon-0.0.dist-info/WHEEL
gavanon-0.0.dist-info/top_level.txt
gavanon-0.0.dist-info/RECORD
