Metadata-Version: 2.1
Name: gavanon
Version: 0.0
Summary: Python package for the Ghent University Gavanon course (Geavanceerd Analoog Ontwerp, English: Advanced Analog Design ).
Author: Senne Vanden Berghe
Author-email: sennevandenberghe2002@gmail.com
License: MIT
Project-URL: Documentation, https://github.com/S3nn3k3/gavanon
Project-URL: Source Code, https://github.com/S3nn3k3/gavanon
Keywords: Advanced Analog Design,Geavanceerd Analoog Ontwerp,Ghent University,Universiteit Gent
Classifier: Development Status :: 4 - Beta
Classifier: Programming Language :: Python :: 3
Classifier: Programming Language :: Python :: 3.8
Classifier: Programming Language :: Python :: 3.9
Classifier: Programming Language :: Python :: 3.10
Classifier: Programming Language :: Python :: 3.11
Classifier: Programming Language :: Python :: 3.12
Classifier: License :: OSI Approved :: MIT License
Classifier: Operating System :: OS Independent
Classifier: Intended Audience :: Education
Classifier: Intended Audience :: Science/Research
Classifier: Intended Audience :: End Users/Desktop
Requires-Python: >=3.8
License-File: LICENSE
Provides-Extra: full
Requires-Dist: control >=0.9 ; extra == 'full'
Requires-Dist: matplotlib >=3.4 ; extra == 'full'
Requires-Dist: numpy >=1.22 ; extra == 'full'
